cucumber_expressions/__init__.py
cucumber_expressions/argument.py
cucumber_expressions/ast.py
cucumber_expressions/combinatorial_generated_expression_factory.py
cucumber_expressions/errors.py
cucumber_expressions/expression.py
cucumber_expressions/expression_generator.py
cucumber_expressions/expression_parser.py
cucumber_expressions/expression_tokenizer.py
cucumber_expressions/generated_expression.py
cucumber_expressions/group.py
cucumber_expressions/group_builder.py
cucumber_expressions/parameter_type.py
cucumber_expressions/parameter_type_matcher.py
cucumber_expressions/parameter_type_registry.py
cucumber_expressions/regular_expression.py
cucumber_expressions/tree_regexp.py
cucumber_expressions-18.0.0.dist-info/LICENSE
cucumber_expressions-18.0.0.dist-info/METADATA
cucumber_expressions-18.0.0.dist-info/WHEEL
cucumber_expressions-18.0.0.dist-info/RECORD
