Metadata-Version: 2.1
Name: cucumber-expressions
Version: 18.0.0
Summary: Cucumber Expressions - a simpler alternative to Regular Expressions
Home-page: https://github.com/cucumber/cucumber-expressions
License: MIT
Keywords: BDD,testing,cucumber,expressions
Author: Jason Allen
Author-email: jsa34@noreply.github.com
Requires-Python: >=3.8,<4.0
Classifier: Development Status :: 3 - Alpha
Classifier: Environment :: Console
Classifier: Intended Audience :: Developers
Classifier: License :: OSI Approved :: MIT License
Classifier: Operating System :: OS Independent
Classifier: Programming Language :: Python :: 3
Classifier: Programming Language :: Python :: 3.8
Classifier: Programming Language :: Python :: 3.9
Classifier: Programming Language :: Python :: 3.10
Classifier: Programming Language :: Python :: 3.11
Classifier: Programming Language :: Python :: 3.12
Classifier: Programming Language :: Python :: Implementation :: CPython
Classifier: Programming Language :: Python :: Implementation :: PyPy
Classifier: Topic :: Software Development :: Libraries :: Python Modules
Classifier: Topic :: Software Development :: Testing
Project-URL: Documentation, https://github.com/cucumber/cucumber-expressions
Project-URL: Repository, https://github.com/cucumber/cucumber-expressions
